MANIFEST.in
README.rst
setup.py
django_xstatic/__init__.py
django_xstatic/finders.py
django_xstatic/storage.py
django_xstatic.egg-info/PKG-INFO
django_xstatic.egg-info/SOURCES.txt
django_xstatic.egg-info/dependency_links.txt
django_xstatic.egg-info/top_level.txt