Metadata-Version: 1.1
Name: django-xstatic
Version: 0.0.2
Summary: Django helpers to use XStatic packages in Django projects
Home-page: http://github.com/gautier/django-xstatic
Author: Gautier Hayoun
Author-email: ghayoun@gmail.com
License: MIT license
Platform: UNKNOWN
Classifier: License :: OSI Approved :: MIT License
Classifier: Development Status :: 3 - Alpha
Classifier: Intended Audience :: Developers
Classifier: Operating System :: OS Independent
Classifier: Programming Language :: Python
Classifier: Topic :: Software Development :: Libraries
Classifier: Topic :: System :: Archiving :: Packaging
Classifier: Topic :: System :: Installation/Setup
Classifier: Topic :: System :: Software Distribution
